{
  "csv_path": "restaurant_reviews.json",
  "session_id": "restaurant_study_2024",
  "sentiment_elements": [
    "aspect_term",
    "aspect_category",
    "sentiment_polarity",
    "opinion_term"
  ],
  "sentiment_polarity_options": [
    "positive",
    "negative",
    "neutral"
  ],
  "aspect_categories": [
    "location general",
    "food prices",
    "food quality",
    "food general",
    "ambience general",
    "service general",
    "restaurant prices",
    "drinks prices",
    "restaurant miscellaneous",
    "drinks quality",
    "drinks style_options",
    "restaurant general",
    "food style_options"
  ],
  "implicit_aspect_term_allowed": true,
  "implicit_opinion_term_allowed": false,
  "auto_clean_phrases": true,
  "save_phrase_positions": true,
  "click_on_token": true,
  "n_few_shot": 10
}


